rate_limiter/__init__.py
rate_limiter/backends/__init__.py
rate_limiter/backends/memory.py
rate_limiter/backends/redis.py
rate_limiter/backends/template.py
tests/__init__.py
tests/test_rate_limiter.py
rate_limiter-0.0.3.dist-info/METADATA
rate_limiter-0.0.3.dist-info/WHEEL
rate_limiter-0.0.3.dist-info/top_level.txt
rate_limiter-0.0.3.dist-info/RECORD
