Metadata-Version: 2.1
Name: rate-limiter
Version: 0.0.3
Summary: A rate limiter which can use any backend
Home-page: https://github.com/shuttl-tech/rate-limiter
Author: Sherub Thakur
Author-email: sherub.thakur@shuttl.com
License: MIT
Classifier: Programming Language :: Python :: 3.7
Provides-Extra: test
